{
    "TRXUSDT": {
        "rank": 1
    },
    "AWEUSDT": {
        "rank": 2
    },
    "KAIAUSDT": {
        "rank": 3
    },
    "SPELLUSDT": {
        "rank": 4
    },
    "OGUSDT": {
        "rank": 5
    },
    "ATUSDT": {
        "rank": 6
    },
    "HIVEUSDT": {
        "rank": 7
    },
    "HYPERUSDT": {
        "rank": 8
    },
    "FFUSDT": {
        "rank": 9
    },
    "EDUUSDT": {
        "rank": 10
    },
    "PAXGUSDT": {
        "rank": 11
    },
    "AEVOUSDT": {
        "rank": 12
    },
    "HAEDALUSDT": {
        "rank": 13
    },
    "DOLOUSDT": {
        "rank": 14
    },
    "SFPUSDT": {
        "rank": 15
    },
    "DEXEUSDT": {
        "rank": 16
    },
    "HMSTRUSDT": {
        "rank": 17
    },
    "B2USDT": {
        "rank": 18
    },
    "RECALLUSDT": {
        "rank": 19
    },
    "1000XECUSDT": {
        "rank": 20
    },
    "WAXPUSDT": {
        "rank": 21
    },
    "TWTUSDT": {
        "rank": 22
    },
    "LUMIAUSDT": {
        "rank": 23
    },
    "AUCTIONUSDT": {
        "rank": 24
    },
    "MANTAUSDT": {
        "rank": 25
    }
}